mcp_server_proj/__init__.py
mcp_server_proj/__main__.py
mcp_server_proj/server.py
mcp_server_proj/core/__init__.py
mcp_server_proj/core/transformation.py
mcp_server_proj-1.0.0.dist-info/METADATA
mcp_server_proj-1.0.0.dist-info/WHEEL
mcp_server_proj-1.0.0.dist-info/entry_points.txt
mcp_server_proj-1.0.0.dist-info/licenses/LICENSE
mcp_server_proj-1.0.0.dist-info/RECORD
