Metadata-Version: 2.4
Name: mcp-server-proj
Version: 1.0.0
Summary: MCP Server PROJ - 坐标系统转换服务器
Project-URL: Homepage, https://github.com/radial-hks/mcp-server-proj
Project-URL: Documentation, https://github.com/radial-hks/mcp-server-proj/blob/main/README.md
Project-URL: Repository, https://github.com/radial-hks/mcp-server-proj.git
Author-email: radial-hks <radialjiajie@gmail.com>
License-Expression: MIT
License-File: LICENSE
Keywords: GIS,MCP,coordinate,projection,transformation
Classifier: Development Status :: 3 - Alpha
Classifier: Intended Audience :: Developers
Classifier: License :: OSI Approved :: MIT License
Classifier: Programming Language :: Python :: 3
Classifier: Programming Language :: Python :: 3.10
Classifier: Topic :: Scientific/Engineering :: GIS
Requires-Python: >=3.10
Requires-Dist: mcp>=1.3.0
Requires-Dist: pyproj>=3.0.0
